examples/__init__.py
examples/example.py
examples/soma.py
sitepipes/__init__.py
sitepipes/config.py
sitepipes/future.py
sitepipes/components/__init__.py
sitepipes/components/abstract.py
sitepipes/components/database.py
sitepipes/components/meta.py
sitepipes/database/__init__.py
sitepipes/database/integrations.py
sitepipes/datasets/__init__.py
sitepipes/datasets/abstract.py
sitepipes/datasets/api.py
sitepipes/datasets/meta.py
sitepipes/models/__init__.py
sitepipes/models/abstract.py
sitepipes/models/meta.py
sitepipes/network/__init__.py
sitepipes/network/abstract.py
sitepipes/network/network.py
sitepipes/network/sites.py
sitepipes/network/worker.py
sitepipes/routes/__init__.py
sitepipes/routes/integrations.py
sitepipes/routes/models.py
sitepipes/routes/workflows.py
sitepipes/util/__init__.py
sitepipes/util/exceptions.py
sitepipes/util/helper.py
sitepipes/util/logger.py
sitepipes-0.1.0.dist-info/LICENSE
sitepipes-0.1.0.dist-info/METADATA
sitepipes-0.1.0.dist-info/WHEEL
sitepipes-0.1.0.dist-info/top_level.txt
sitepipes-0.1.0.dist-info/RECORD
