Metadata-Version: 2.1
Name: sitepipes
Version: 0.1.0
Summary: A framework for federated data networks with web components.
Home-page: https://github.com/MedleyLabs/sitepipes
Author: Eric Yates
Author-email: eric@medleyagency.com
License: 
